[
  {
    "source_id": "https://doi.org/10.34191/OFR-757",
    "record_id": "1602",
    "name": "Oyler Mine",
    "location_info": {
      "country": [
        {
          "source": "UMN Matching System v1",
          "confidence": 1.0,
          "observed_name": "United States",
          "normalized_uri": "https://minmod.isi.edu/resource/Q1235"
        }
      ],
      "state_or_province": [
        {
          "source": "UMN Matching System v1",
          "confidence": 1.0,
          "observed_name": "Utah",
          "normalized_uri": "https://minmod.isi.edu/resource/Q6897"
        }
      ],
      "crs": {
        "source": "UMN Matching System v1",
        "confidence": 1.0,
        "observed_name": "EPSG:26912",
        "normalized_uri": "https://minmod.isi.edu/resource/Q704"
      },
      "location": "POINT (479757 4234634)"
    },
    "mineral_inventory": [
      {
        "reference": {
          "document": {
            "uri": "https://doi.org/10.34191/OFR-757"
          }
        },
        "commodity": {
          "source": "UMN Matching System v1",
          "confidence": 1.0,
          "observed_name": "U",
          "normalized_uri": "https://minmod.isi.edu/resource/Q588"
        }
      }
    ],
    "reference": [
      {
        "document": {
          "uri": "https://doi.org/10.34191/OFR-757"
        }
      }
    ],
    "created_by": "https://minmod.isi.edu/users/s/umn",
    "modified_at": "2024-10-23T20:05:59Z"
  },
  {
    "source_id": "https://doi.org/10.34191/OFR-757",
    "record_id": "5669",
    "name": "Copper King Prospect",
    "location_info": {
      "country": [
        {
          "source": "UMN Matching System v1",
          "confidence": 1.0,
          "observed_name": "United States",
          "normalized_uri": "https://minmod.isi.edu/resource/Q1235"
        }
      ],
      "state_or_province": [
        {
          "source": "UMN Matching System v1",
          "confidence": 1.0,
          "observed_name": "Utah",
          "normalized_uri": "https://minmod.isi.edu/resource/Q6897"
        }
      ],
      "crs": {
        "source": "UMN Matching System v1",
        "confidence": 1.0,
        "observed_name": "EPSG:26912",
        "normalized_uri": "https://minmod.isi.edu/resource/Q704"
      },
      "location": "POINT (242575 4115053)"
    },
    "mineral_inventory": [
      {
        "reference": {
          "document": {
            "uri": "https://doi.org/10.34191/OFR-757"
          }
        },
        "commodity": {
          "source": "UMN Matching System v1",
          "confidence": 1.0,
          "observed_name": "CU",
          "normalized_uri": "https://minmod.isi.edu/resource/Q538"
        }
      }
    ],
    "reference": [
      {
        "document": {
          "uri": "https://doi.org/10.34191/OFR-757"
        }
      }
    ],
    "created_by": "https://minmod.isi.edu/users/s/umn",
    "modified_at": "2024-10-23T20:05:59Z"
  }
]